README.md
setup.py
cbpy/__init__.py
cbpy/chaos_optim.py
cbpy/dataset.py
cbpy/net.py
cbpy/plot.py
cbpy/train.py
cbpy/utils.py
cbpy.egg-info/PKG-INFO
cbpy.egg-info/SOURCES.txt
cbpy.egg-info/dependency_links.txt
cbpy.egg-info/requires.txt
cbpy.egg-info/top_level.txt