Metadata-Version: 2.1
Name: cbpy
Version: 0.0.1
Summary: Implement Chaotic Backpropagation Algorithm
Home-page: https://github.com/PengTao-HUST/CBP
Author: Peng Tao
Author-email: taopeng543@gmail.com
License: MIT Licence
Platform: UNKNOWN
Classifier: Programming Language :: Python :: 3
Classifier: License :: OSI Approved :: MIT License
Requires-Python: >=3.6
